{
  "id": "hubspot",
  "name": "HubSpot",
  "description": "Manage HubSpot CRM contacts, companies, deals, and tickets. Search and update records, track sales pipelines, and automate CRM workflows through AI chat.",
  "category": "CRM",
  "icon_url": "icons/hubspot.png",
  "server_type": "http",
  "command": null,
  "args": null,
  "url": "https://mcp.hubspot.com",
  "org_auth_type": "oauth2",
  "user_auth_type": "oauth2",
  "oauth_config": {
    "authorization_url": "https://app.hubspot.com/oauth/authorize",
    "token_url": "https://api.hubapi.com/oauth/v1/token",
    "scopes": "crm.objects.contacts.read crm.objects.companies.read crm.objects.deals.read",
    "scope_param_name": "scope"
  },
  "credentials_needed": ["client_id", "client_secret"],
  "user_auth_instructions": "Click 'Connect' to link your HubSpot account.\nYou'll be prompted to select your HubSpot account and grant permissions.",
  "setup_notes": "Uses HubSpot's official remote MCP server.\n\nAdmin setup:\n1. Go to your HubSpot account > Development > MCP Auth Apps\n2. Create a new MCP Auth App\n3. Set the app name, redirect URL, and optional icon\n4. Copy the Client ID and Client Secret\n5. The server uses OAuth 2.1 with PKCE for authentication\n\nCurrently supports read-only access to: contacts, companies,\ndeals, tickets, products, orders, line items, invoices, quotes.",
  "tags": ["hubspot", "crm", "sales", "contacts", "deals", "marketing", "pipeline"],
  "source": {
    "docs": "https://developers.hubspot.com/mcp"
  }
}
